[
    {
        "date": "03/10/2021 12:37:05",
        "failed": 493,
        "passed": 428,
        "skipped": 0,
        "versions": [
            {
                "name": "onnx",
                "version": "1.8.1"
            },
            {
                "name": "torch",
                "version": "1.9.0a0+git6aa5148"
            }
        ]
    },
    {
        "date": "03/10/2021 15:16:25",
        "failed": 493,
        "passed": 428,
        "skipped": 0,
        "versions": [
            {
                "name": "onnx",
                "version": "1.8.1"
            },
            {
                "name": "torch",
                "version": "1.9.0a0+git6aa5148"
            }
        ]
    },
    {
        "date": "03/11/2021 02:44:39",
        "failed": 493,
        "passed": 428,
        "skipped": 0,
        "versions": [
            {
                "name": "onnx",
                "version": "1.8.1"
            },
            {
                "name": "torch",
                "version": "1.9.0a0+git4351d09"
            }
        ]
    },
    {
        "date": "03/12/2021 03:00:49",
        "failed": 493,
        "passed": 428,
        "skipped": 0,
        "versions": [
            {
                "name": "onnx",
                "version": "1.8.1"
            },
            {
                "name": "torch",
                "version": "1.9.0a0+gitb9e900e"
            }
        ]
    },
    {
        "date": "03/13/2021 02:44:01",
        "failed": 493,
        "passed": 428,
        "skipped": 0,
        "versions": [
            {
                "name": "onnx",
                "version": "1.8.1"
            },
            {
                "name": "torch",
                "version": "1.9.0a0+git5b648ef"
            }
        ]
    },
    {
        "date": "03/14/2021 02:47:01",
        "failed": 493,
        "passed": 428,
        "skipped": 0,
        "versions": [
            {
                "name": "onnx",
                "version": "1.8.1"
            },
            {
                "name": "torch",
                "version": "1.9.0a0+git84af0c7"
            }
        ]
    },
    {
        "date": "03/15/2021 02:34:58",
        "failed": 493,
        "passed": 428,
        "skipped": 0,
        "versions": [
            {
                "name": "onnx",
                "version": "1.8.1"
            },
            {
                "name": "torch",
                "version": "1.9.0a0+gitf6df18f"
            }
        ]
    },
    {
        "date": "03/16/2021 03:05:52",
        "failed": 493,
        "passed": 428,
        "skipped": 0,
        "versions": [
            {
                "name": "onnx",
                "version": "1.8.1"
            },
            {
                "name": "torch",
                "version": "1.9.0a0+gitee35060"
            }
        ]
    },
    {
        "date": "03/17/2021 02:55:11",
        "failed": 493,
        "passed": 428,
        "skipped": 0,
        "versions": [
            {
                "name": "onnx",
                "version": "1.8.1"
            },
            {
                "name": "torch",
                "version": "1.9.0a0+gitc4f5016"
            }
        ]
    },
    {
        "date": "03/18/2021 02:32:05",
        "failed": 493,
        "passed": 428,
        "skipped": 0,
        "versions": [
            {
                "name": "onnx",
                "version": "1.8.1"
            },
            {
                "name": "torch",
                "version": "1.9.0a0+git2eb3917"
            }
        ]
    },
    {
        "date": "03/19/2021 02:19:46",
        "failed": 493,
        "passed": 428,
        "skipped": 0,
        "versions": [
            {
                "name": "onnx",
                "version": "1.8.1"
            },
            {
                "name": "torch",
                "version": "1.9.0a0+git04e0cbf"
            }
        ]
    },
    {
        "date": "03/20/2021 03:01:30",
        "failed": 493,
        "passed": 428,
        "skipped": 0,
        "versions": [
            {
                "name": "onnx",
                "version": "1.8.1"
            },
            {
                "name": "torch",
                "version": "1.9.0a0+git270d675"
            }
        ]
    },
    {
        "date": "03/21/2021 02:58:47",
        "failed": 493,
        "passed": 428,
        "skipped": 0,
        "versions": [
            {
                "name": "onnx",
                "version": "1.8.1"
            },
            {
                "name": "torch",
                "version": "1.9.0a0+git8294bff"
            }
        ]
    },
    {
        "date": "03/22/2021 02:40:53",
        "failed": 493,
        "passed": 428,
        "skipped": 0,
        "versions": [
            {
                "name": "onnx",
                "version": "1.8.1"
            },
            {
                "name": "torch",
                "version": "1.9.0a0+gitfc58b3f"
            }
        ]
    }
]